kentikapi/__init__.py
kentikapi/v5/__init__.py
kentikapi/v5/tagging.py
kentikapi-0.1.10.dist-info/LICENSE.txt
kentikapi-0.1.10.dist-info/METADATA
kentikapi-0.1.10.dist-info/RECORD
kentikapi-0.1.10.dist-info/WHEEL
kentikapi-0.1.10.dist-info/top_level.txt
