Metadata-Version: 2.1
Name: kentikapi
Version: 0.1.10
Summary: Kentik API Client
Home-page: https://github.com/kentik/api-client
Author: Blake Caldwell
Author-email: UNKNOWN
License: LICENSE.txt
Platform: UNKNOWN
Requires-Dist: requests
